xyzgraph/__init__.py
xyzgraph/ascii_renderer.py
xyzgraph/cli.py
xyzgraph/compare.py
xyzgraph/config.py
xyzgraph/data_loader.py
xyzgraph/graph_builders.py
xyzgraph/orca_parser.py
xyzgraph/utils.py
xyzgraph/data/__init__.py
xyzgraph/data/atom_symbols.json
xyzgraph/data/expected_valences.json
xyzgraph/data/valence_electrons.json
xyzgraph/data/vdw_radii.json
xyzgraph-1.4.9.dist-info/licenses/LICENSE
xyzgraph-1.4.9.dist-info/METADATA
xyzgraph-1.4.9.dist-info/WHEEL
xyzgraph-1.4.9.dist-info/entry_points.txt
xyzgraph-1.4.9.dist-info/top_level.txt
xyzgraph-1.4.9.dist-info/RECORD
