Metadata-Version: 2.4
Name: xyzgraph
Version: 1.4.9
Summary: Molecular Graph Construction from Cartesian Coordinates.
Author: Dr Alister Goodfellow
Project-URL: homepage, https://github.com/aligfellow/xyzgraph
Classifier: Programming Language :: Python :: 3
Classifier: License :: OSI Approved :: MIT License
Classifier: Operating System :: OS Independent
Requires-Python: >=3.8
License-File: LICENSE
Requires-Dist: numpy
Requires-Dist: rdkit
Requires-Dist: networkx
Dynamic: license-file
